[
  {
    "autoria": "Melina González",
    "pubDate": "Jun 28 2023",
    "anio": "2024",
    "escuela": "Escuela Técnica de la Universidad de Buenos Aires",
    "curso": "1B",
    "content": "La noche oscura.<br/><br/>\nEl cielo es muy brillante.<br/><br/>\nAtardecer."
  },
  {
    "autoria": "Abigail Gómez",
    "pubDate": "May 27 2023",
    "anio": "2023",
    "escuela": "Escuela Técnica de la Universidad de Buenos Aires",
    "curso": "1D",
    "content": "Como en el bosque<br/>\ncazador seré por ti<br/>\nmi bella presa."
  },
  {
    "autoria": "Alan Chávez",
    "pubDate": "May 27 2023",
    "anio": "2023",
    "escuela": "Escuela Técnica de la Universidad de Buenos Aires",
    "curso": "1D",
    "content": "Notas armónicas<br/>\nme colmarán de calma<br/>\nen el silencio."
  },
  {
    "autoria": "Alison Estrada",
    "pubDate": "May 27 2023",
    "anio": "2023",
    "escuela": "Escuela Técnica de la Universidad de Buenos Aires",
    "curso": "1D",
    "content": "Noche sin luna<br/>\nla tempestad estrujó<br/>\nlos viejos cedros."
  },
  {
    "autoria": "Mía Ledesma",
    "pubDate": "May 27 2023",
    "anio": "2023",
    "escuela": "Escuela Técnica de la Universidad de Buenos Aires",
    "curso": "1D",
    "content": "Amor que brilla<br/>\nEn el calor nocturno<br/>\nTiernas caricias."
  },
  {
    "autoria": "Zaira González",
    "pubDate": "May 27 2023",
    "anio": "2023",
    "escuela": "Escuela Técnica de la Universidad de Buenos Aires",
    "curso": "1D",
    "content": "La noche oscura.<br/><br/>\nEl cielo es muy brillante.<br/><br/>\nAmanecer."
  },
  {
    "autoria": "Daniel Fernández",
    "pubDate": "May 27 2023",
    "anio": "2023",
    "escuela": "Escuela Técnica de la Universidad de Buenos Aires",
    "curso": "1D",
    "content": "Mueven las piezas<br/>\npasa el atardecer<br/>\ntermina el juego."
  },
  {
    "autoria": "Erik Guzmán",
    "pubDate": "May 27 2023",
    "anio": "2023",
    "escuela": "Escuela Técnica de la Universidad de Buenos Aires",
    "curso": "1D",
    "content": "Babosas casas<br/>\nnaturalmente llevan<br/>\nlos caracoles."
  },
  {
    "autoria": "Florentino Santa Cruz",
    "pubDate": "May 27 2023",
    "anio": "2023",
    "escuela": "Escuela Técnica de la Universidad de Buenos Aires",
    "curso": "1D",
    "content": "Es primavera,<br/>\nlas flores son felices<br/>\nhabiendo calma."
  },
  {
    "autoria": "Gonzalo Cohin",
    "pubDate": "May 27 2023",
    "anio": "2023",
    "escuela": "Escuela Técnica de la Universidad de Buenos Aires",
    "curso": "1D",
    "content": "Algo tan bueno<br/>\nque yo no cambiaría<br/>\nni por dinero."
  },
  {
    "autoria": "Guillermo Alarcón",
    "pubDate": "May 27 2023",
    "anio": "2023",
    "escuela": "Escuela Técnica de la Universidad de Buenos Aires",
    "curso": "1D",
    "content": "Las flores brillan,<br/>\nel otoño del árbol,<br/>\nestá la noche."
  },
  {
    "autoria": "Henry Patzi Ticona",
    "pubDate": "May 27 2023",
    "anio": "2023",
    "escuela": "Escuela Técnica de la Universidad de Buenos Aires",
    "curso": "1D",
    "content": "Brisa del aire\\s<br/>\nse mueven hojas del árbol<br/>\nhabiendo calma."
  },
  {
    "autoria": "Jorge Mamani Algarañáz",
    "pubDate": "May 27 2023",
    "anio": "2023",
    "escuela": "Escuela Técnica de la Universidad de Buenos Aires",
    "curso": "1D",
    "content": "Parte nocturna<br/>\nla luz oscura del sol,<br/>\nla tierra duerme."
  },
  {
    "autoria": "Antonela Ticona",
    "pubDate": "May 27 2023",
    "anio": "2023",
    "escuela": "Escuela Técnica de la Universidad de Buenos Aires",
    "curso": "1D",
    "content": "Jazmín fragante<br/>\nTu fragancia tan suave<br/>\nVibra en el aire."
  },
  {
    "autoria": "Luca Rodríguez Vilaró",
    "pubDate": "May 27 2023",
    "anio": "2023",
    "escuela": "Escuela Técnica de la Universidad de Buenos Aires",
    "curso": "1D",
    "content": "Al atardecer<br/>\nsí me hace sombra el sol<br/>\nen el paseo."
  },
  {
    "autoria": "Ludmila Silva",
    "pubDate": "May 27 2023",
    "anio": "2023",
    "escuela": "Escuela Técnica de la Universidad de Buenos Aires",
    "curso": "1D",
    "content": "Las hojas caen.<br/>\nY el cielo brilla tarde<br/>\n<br/>\nen el verano."
  },
  {
    "autoria": "Mateo Fernández",
    "pubDate": "May 27 2023",
    "anio": "2023",
    "escuela": "Escuela Técnica de la Universidad de Buenos Aires",
    "curso": "1D",
    "content": "Las flores cuelgan<br/>\nmarchitas de otoño,<br/>\nvuelve el invierno."
  },
  {
    "autoria": "Mayra González",
    "pubDate": "May 27 2023",
    "anio": "2023",
    "escuela": "Escuela Técnica de la Universidad de Buenos Aires",
    "curso": "1D",
    "content": "El sol brillante,<br/>\nla noche se esfumó.<br/>\n<br/>\nHoy nuevo día."
  },
  {
    "autoria": "Nataly Tinuco",
    "pubDate": "May 27 2023",
    "anio": "2023",
    "escuela": "Escuela Técnica de la Universidad de Buenos Aires",
    "curso": "1D",
    "content": "Quiero decirlo<br/>\nlas flores no me dejan<br/>\nmi voz ya no ve."
  },
  {
    "autoria": "Romero",
    "pubDate": "May 27 2023",
    "anio": "2023",
    "escuela": "Escuela Técnica de la Universidad de Buenos Aires",
    "curso": "1D",
    "content": "Habiendo calma<br/>\nla más mínima brisa<br/>\nparece viento."
  },
  {
    "autoria": "Sebastián Espinilla",
    "pubDate": "May 27 2023",
    "anio": "2023",
    "escuela": "Escuela Técnica de la Universidad de Buenos Aires",
    "curso": "1D",
    "content": "Durante el alba<br/>\namanece en el mar<br/>\nde las mil vidas."
  },
  {
    "autoria": "Thiago Romero",
    "pubDate": "May 27 2023",
    "anio": "2023",
    "escuela": "Escuela Técnica de la Universidad de Buenos Aires",
    "curso": "1D",
    "content": "La noche oscura<br/>\ncon ganas de bailar<br/>\ncon las estrellas."
  },
  {
    "autoria": "Tobías Benítez",
    "pubDate": "May 27 2023",
    "anio": "2023",
    "escuela": "Escuela Técnica de la Universidad de Buenos Aires",
    "curso": "1D",
    "content": "Hojas del árbol<br/>\nen el otoño caen<br/>\nen la tierra."
  },
  {
    "autoria": "Camila Vargas Pinto",
    "pubDate": "May 27 2023",
    "anio": "2023",
    "escuela": "Escuela Técnica de la Universidad de Buenos Aires",
    "curso": "1D",
    "content": "El sol brilloso<br/>\ncamina con nosotros<br/>\ny se apaga."
  }
]